<?xml version="1.0" encoding="windows-1252" ?>
<adfc-config xmlns="http://xmlns.oracle.com/adf/controller" version="1.2">
  <view id="clTable">
    <page>/clTable.jspx</page>
  </view>
  <task-flow-call id="NuevoCliente">
    <task-flow-reference>
      <document>/WEB-INF/NuevoCliente.xml</document>
      <id>NuevoCliente</id>
    </task-flow-reference>
  </task-flow-call>
  <control-flow-rule id="__1">
    <from-activity-id id="__2">clTable</from-activity-id>
    <control-flow-case id="__4">
      <from-outcome id="__6">nuevoCliente</from-outcome>
      <to-activity-id id="__3">NuevoCliente</to-activity-id>
    </control-flow-case>
  </control-flow-rule>
</adfc-config>
